LICENSE
MANIFEST.in
README.md
requirements.txt
setup.py
job_client_graphql/__init__.py
job_client_graphql/__meta__.py
job_client_graphql/cell_display.py
job_client_graphql/client.py
job_client_graphql/client_graphql_http.py
job_client_graphql/client_graphql_ws.py
job_client_graphql/store.py
job_client_graphql/util.py
job_client_graphql/w_socket.py
job_client_graphql.egg-info/PKG-INFO
job_client_graphql.egg-info/SOURCES.txt
job_client_graphql.egg-info/dependency_links.txt
job_client_graphql.egg-info/not-zip-safe
job_client_graphql.egg-info/requires.txt
job_client_graphql.egg-info/top_level.txt