Metadata-Version: 1.1
Name: job-client-graphql
Version: 0.1.0
Summary: graphql client in for jupyter-observablehq-bridge
Home-page: https://github.com/jupyter-observablehq-bridge/job-client-graphql
Author: jupyter-observablehq-bridge
Author-email: olivier.borderies@gmail.com
License: NO
Download-URL: https://github.com/jupyter-observablehq-bridge/job-client-graphql/tarball/0.1.0
Keywords: jupyter,observablehq,graphql,client
Platform: UNKNOWN
Classifier: Development Status :: 4 - Beta
Classifier: License :: OSI Approved :: MIT License
Classifier: Programming Language :: Python :: 3.6
Classifier: Programming Language :: Python :: 3.7
Classifier: Programming Language :: Python :: 3.8
